[
  {
    "title": "TencentARC/GFPGAN",
    "url": "https://github.com/TencentARC/GFPGAN",
    "desc": "GFPGAN aims at developing Practical Algorithms for Real-world Face Restoration.",
    "lang": "Python"
  },
  {
    "title": "tsherif/space-shooter.c",
    "url": "https://github.com/tsherif/space-shooter.c",
    "desc": "A cross-platform, top-down 2D space shooter written in C using only system libraries.",
    "lang": "C"
  },
  {
    "title": "ossu/computer-science",
    "url": "https://github.com/ossu/computer-science",
    "desc": "🎓 Path to a free self-taught education in Computer Science!"
  },
  {
    "title": "yt-dlp/yt-dlp",
    "url": "https://github.com/yt-dlp/yt-dlp",
    "desc": "A youtube-dl fork with additional features and fixes",
    "lang": "Python"
  },
  {
    "title": "CorentinJ/Real-Time-Voice-Cloning",
    "url": "https://github.com/CorentinJ/Real-Time-Voice-Cloning",
    "desc": "Clone a voice in 5 seconds to generate arbitrary speech in real-time",
    "lang": "Python"
  },
  {
    "title": "PCSX2/pcsx2",
    "url": "https://github.com/PCSX2/pcsx2",
    "desc": "PCSX2 - The Playstation 2 Emulator",
    "lang": "C++"
  },
  {
    "title": "anchore/syft",
    "url": "https://github.com/anchore/syft",
    "desc": "CLI tool and library for generating a Software Bill of Materials from container images and filesystems",
    "lang": "Go"
  },
  {
    "title": "SergioBenitez/Rocket",
    "url": "https://github.com/SergioBenitez/Rocket",
    "desc": "A web framework for Rust.",
    "lang": "Rust"
  },
  {
    "title": "projectdiscovery/nuclei",
    "url": "https://github.com/projectdiscovery/nuclei",
    "desc": "Fast and customizable vulnerability scanner based on simple YAML based DSL.",
    "lang": "Go"
  },
  {
    "title": "eclypsium/mikrotik_meris_checker",
    "url": "https://github.com/eclypsium/mikrotik_meris_checker",
    "desc": "This tool will check a list of IP addresses of RouterOS-based routers to validate if they were infected with Meris.",
    "lang": "C++"
  },
  {
    "title": "logseq/logseq",
    "url": "https://github.com/logseq/logseq",
    "desc": "A privacy-first, open-source platform for knowledge management and collaboration. Desktop app download link: https://github.com/logseq/logseq/releases, roadmap: https://trello.com/b/8txSM12G/roadmap",
    "lang": "Clojure"
  },
  {
    "title": "CSSEGISandData/COVID-19",
    "url": "https://github.com/CSSEGISandData/COVID-19",
    "desc": "Novel Coronavirus (COVID-19) Cases, provided by JHU CSSE"
  },
  {
    "title": "NationalSecurityAgency/ghidra",
    "url": "https://github.com/NationalSecurityAgency/ghidra",
    "desc": "Ghidra is a software reverse engineering (SRE) framework",
    "lang": "Java"
  },
  {
    "title": "FirebaseExtended/flutterfire",
    "url": "https://github.com/FirebaseExtended/flutterfire",
    "desc": "🔥 A collection of Firebase plugins for Flutter apps.",
    "lang": "Dart"
  },
  {
    "title": "floodsung/Deep-Learning-Papers-Reading-Roadmap",
    "url": "https://github.com/floodsung/Deep-Learning-Papers-Reading-Roadmap",
    "desc": "Deep Learning papers reading roadmap for anyone who are eager to learn this amazing tech!",
    "lang": "Python"
  },
  {
    "title": "mli/paper-reading",
    "url": "https://github.com/mli/paper-reading",
    "desc": "深度学习经典、新论文逐段精读"
  },
  {
    "title": "tailwindlabs/tailwindcss",
    "url": "https://github.com/tailwindlabs/tailwindcss",
    "desc": "A utility-first CSS framework for rapid UI development.",
    "lang": "JavaScript"
  },
  {
    "title": "ruffle-rs/ruffle",
    "url": "https://github.com/ruffle-rs/ruffle",
    "desc": "A Flash Player emulator written in Rust",
    "lang": "Rust"
  },
  {
    "title": "minitorch/minitorch",
    "url": "https://github.com/minitorch/minitorch",
    "desc": "The full minitorch student suite.",
    "lang": "Python"
  },
  {
    "title": "projectdiscovery/interactsh",
    "url": "https://github.com/projectdiscovery/interactsh",
    "desc": "An OOB interaction gathering server and client library",
    "lang": "Go"
  },
  {
    "title": "HashLips/hashlips_art_engine",
    "url": "https://github.com/HashLips/hashlips_art_engine",
    "desc": "HashLips Art Engine is a tool used to create multiple different instances of artworks based on provided layers.",
    "lang": "JavaScript"
  },
  {
    "title": "solana-labs/token-list",
    "url": "https://github.com/solana-labs/token-list",
    "desc": "The community maintained Solana token registry",
    "lang": "Go"
  },
  {
    "title": "apache/logging-log4j2",
    "url": "https://github.com/apache/logging-log4j2",
    "desc": "Apache Log4j 2 is an upgrade to Log4j that provides significant improvements over its predecessor, Log4j 1.x, and provides many of the improvements available in Logback while fixing some inherent problems in Logback's architecture.",
    "lang": "Java"
  },
  {
    "title": "TheAlgorithms/Python",
    "url": "https://github.com/TheAlgorithms/Python",
    "desc": "All Algorithms implemented in Python",
    "lang": "Python"
  },
  {
    "title": "itzg/docker-minecraft-server",
    "url": "https://github.com/itzg/docker-minecraft-server",
    "desc": "Docker image that provides a Minecraft Server that will automatically download selected version at startup",
    "lang": "Shell"
  }
]